CJKrelate/__init__.py
CJKrelate/decompose.py
CJKrelate/dir.py
CJKrelate/frequency.py
CJKrelate/image.py
CJKrelate/radicalize.py
CJKrelate/sort.py
CJKrelate/variant.py
CJKrelate/chinese/__init__.py
CJKrelate/japanese/__init__.py
CJKrelate-0.1.2.dist-info/METADATA
CJKrelate-0.1.2.dist-info/RECORD
CJKrelate-0.1.2.dist-info/WHEEL
CJKrelate-0.1.2.dist-info/top_level.txt
